soccerxcomm/__init__.py
soccerxcomm/client.py
soccerxcomm/game_info.py
soccerxcomm/game_stage_kind.py
soccerxcomm/http_client.py
soccerxcomm/http_server.py
soccerxcomm/logger.py
soccerxcomm/message.py
soccerxcomm/network_client_interface.py
soccerxcomm/network_server_interface.py
soccerxcomm/robot_control.py
soccerxcomm/robot_status.py
soccerxcomm/server.py
soccerxcomm-0.3.0.dist-info/LICENSE
soccerxcomm-0.3.0.dist-info/METADATA
soccerxcomm-0.3.0.dist-info/WHEEL
soccerxcomm-0.3.0.dist-info/RECORD
